[
  {
    "epoch": 1,
    "loss": 6.665045416355133
  },
  {
    "epoch": 2,
    "loss": 1.5777314418554307
  },
  {
    "epoch": 3,
    "loss": 0.29342075660824773
  },
  {
    "epoch": 4,
    "loss": 0.22034696646034718
  },
  {
    "epoch": 5,
    "loss": 0.19706620678305625
  },
  {
    "epoch": 6,
    "loss": 0.18849477641284465
  },
  {
    "epoch": 7,
    "loss": 0.18452211298048496
  },
  {
    "epoch": 8,
    "loss": 0.18464648194611072
  },
  {
    "epoch": 9,
    "loss": 0.16762480027973653
  },
  {
    "epoch": 10,
    "loss": 0.1626320858299732
  },
  {
    "epoch": 11,
    "loss": 0.15458736442029475
  },
  {
    "epoch": 12,
    "loss": 0.1523250474780798
  },
  {
    "epoch": 13,
    "loss": 0.1483688449114561
  },
  {
    "epoch": 14,
    "loss": 0.1550444347411394
  },
  {
    "epoch": 15,
    "loss": 0.1534048454090953
  },
  {
    "epoch": 16,
    "loss": 0.146896903924644
  },
  {
    "epoch": 17,
    "loss": 0.14468557205051183
  },
  {
    "epoch": 18,
    "loss": 0.146533039547503
  },
  {
    "epoch": 19,
    "loss": 0.15022510897368194
  },
  {
    "epoch": 20,
    "loss": 0.14170418001711368
  },
  {
    "epoch": 21,
    "loss": 0.15227329261600972
  },
  {
    "epoch": 22,
    "loss": 0.1421169474720955
  },
  {
    "epoch": 23,
    "loss": 0.13597410798072815
  },
  {
    "epoch": 24,
    "loss": 0.13530656848102807
  },
  {
    "epoch": 25,
    "loss": 0.14054759092628955
  },
  {
    "epoch": 26,
    "loss": 0.13090942077338696
  },
  {
    "epoch": 27,
    "loss": 0.1382159651070833
  },
  {
    "epoch": 28,
    "loss": 0.13666922897100447
  },
  {
    "epoch": 29,
    "loss": 0.13345401346683503
  },
  {
    "epoch": 30,
    "loss": 0.1324664932116866
  },
  {
    "epoch": 31,
    "loss": 0.13507527254521848
  },
  {
    "epoch": 32,
    "loss": 0.1345901172608137
  },
  {
    "epoch": 33,
    "loss": 0.13569243106991052
  },
  {
    "epoch": 34,
    "loss": 0.13111108876764774
  },
  {
    "epoch": 35,
    "loss": 0.13451668471097947
  },
  {
    "epoch": 36,
    "loss": 0.1321382651850581
  }
]