[
  {
    "epoch": 1,
    "loss": 6.386027073860168
  },
  {
    "epoch": 2,
    "loss": 1.2964728784561157
  },
  {
    "epoch": 3,
    "loss": 0.6607793089747429
  },
  {
    "epoch": 4,
    "loss": 0.5773327416181564
  },
  {
    "epoch": 5,
    "loss": 0.5498267030715942
  },
  {
    "epoch": 6,
    "loss": 0.5091848701238633
  },
  {
    "epoch": 7,
    "loss": 0.5022267279028892
  },
  {
    "epoch": 8,
    "loss": 0.4819972005486488
  },
  {
    "epoch": 9,
    "loss": 0.4749099038541317
  },
  {
    "epoch": 10,
    "loss": 0.4775433439016342
  },
  {
    "epoch": 11,
    "loss": 0.4549134474992752
  },
  {
    "epoch": 12,
    "loss": 0.4473570816218853
  },
  {
    "epoch": 13,
    "loss": 0.4409404321014881
  },
  {
    "epoch": 14,
    "loss": 0.4345905175805092
  },
  {
    "epoch": 15,
    "loss": 0.43644040524959565
  },
  {
    "epoch": 16,
    "loss": 0.4241576555371285
  },
  {
    "epoch": 17,
    "loss": 0.42604652911424634
  },
  {
    "epoch": 18,
    "loss": 0.4173639792203903
  },
  {
    "epoch": 19,
    "loss": 0.4167300044000149
  },
  {
    "epoch": 20,
    "loss": 0.4274877551198006
  },
  {
    "epoch": 21,
    "loss": 0.40930374071002007
  },
  {
    "epoch": 22,
    "loss": 0.411870656311512
  },
  {
    "epoch": 23,
    "loss": 0.4077226176857948
  },
  {
    "epoch": 24,
    "loss": 0.4086503486335278
  },
  {
    "epoch": 25,
    "loss": 0.4005735722184181
  },
  {
    "epoch": 26,
    "loss": 0.40168335929512977
  },
  {
    "epoch": 27,
    "loss": 0.40217349484562875
  },
  {
    "epoch": 28,
    "loss": 0.4104964578151703
  },
  {
    "epoch": 29,
    "loss": 0.389827072173357
  },
  {
    "epoch": 30,
    "loss": 0.3880481797456741
  },
  {
    "epoch": 31,
    "loss": 0.3876485422253609
  },
  {
    "epoch": 32,
    "loss": 0.39385121673345563
  },
  {
    "epoch": 33,
    "loss": 0.3827269098162651
  },
  {
    "epoch": 34,
    "loss": 0.39593200087547303
  },
  {
    "epoch": 35,
    "loss": 0.3834395690262318
  },
  {
    "epoch": 36,
    "loss": 0.3833027793467045
  },
  {
    "epoch": 37,
    "loss": 0.38562468901276586
  },
  {
    "epoch": 38,
    "loss": 0.37525741204619406
  },
  {
    "epoch": 39,
    "loss": 0.3743709249794483
  },
  {
    "epoch": 40,
    "loss": 0.37803828984498977
  },
  {
    "epoch": 41,
    "loss": 0.37769640862941745
  },
  {
    "epoch": 42,
    "loss": 0.3722494702041149
  },
  {
    "epoch": 43,
    "loss": 0.37516399592161176
  },
  {
    "epoch": 44,
    "loss": 0.3849619956314564
  },
  {
    "epoch": 45,
    "loss": 0.3670055501163006
  },
  {
    "epoch": 46,
    "loss": 0.3687673769891262
  },
  {
    "epoch": 47,
    "loss": 0.36271644338965414
  },
  {
    "epoch": 48,
    "loss": 0.3641983188688755
  },
  {
    "epoch": 49,
    "loss": 0.36373801112174986
  },
  {
    "epoch": 50,
    "loss": 0.3714760136604309
  },
  {
    "epoch": 51,
    "loss": 0.3736598528921604
  },
  {
    "epoch": 52,
    "loss": 0.35652891144156457
  },
  {
    "epoch": 53,
    "loss": 0.36108139365911485
  },
  {
    "epoch": 54,
    "loss": 0.36087232261896135
  },
  {
    "epoch": 55,
    "loss": 0.36339072450995447
  },
  {
    "epoch": 56,
    "loss": 0.3558232013881206
  },
  {
    "epoch": 57,
    "loss": 0.3515150763094425
  },
  {
    "epoch": 58,
    "loss": 0.35029543936252594
  },
  {
    "epoch": 59,
    "loss": 0.3466353589296341
  },
  {
    "epoch": 60,
    "loss": 0.36423335403203966
  },
  {
    "epoch": 61,
    "loss": 0.3549670659005642
  },
  {
    "epoch": 62,
    "loss": 0.35620762437582015
  },
  {
    "epoch": 63,
    "loss": 0.34955601274967196
  },
  {
    "epoch": 64,
    "loss": 0.34890978917479515
  },
  {
    "epoch": 65,
    "loss": 0.3509967878460884
  },
  {
    "epoch": 66,
    "loss": 0.35159081414341925
  },
  {
    "epoch": 67,
    "loss": 0.35839946553111074
  },
  {
    "epoch": 68,
    "loss": 0.3558129028975964
  },
  {
    "epoch": 69,
    "loss": 0.3544209849834442
  }
]