[
  {
    "epoch": 1,
    "loss": 7.5958579158782955
  },
  {
    "epoch": 2,
    "loss": 3.0165304839611053
  },
  {
    "epoch": 3,
    "loss": 1.3675345361232758
  },
  {
    "epoch": 4,
    "loss": 1.2664141607284547
  },
  {
    "epoch": 5,
    "loss": 1.1783286017179488
  },
  {
    "epoch": 6,
    "loss": 1.1718258064985276
  },
  {
    "epoch": 7,
    "loss": 1.1770847064256669
  },
  {
    "epoch": 8,
    "loss": 1.177879753112793
  },
  {
    "epoch": 9,
    "loss": 1.1546854555606842
  },
  {
    "epoch": 10,
    "loss": 1.161318929195404
  },
  {
    "epoch": 11,
    "loss": 1.1216688114404678
  },
  {
    "epoch": 12,
    "loss": 1.1045599859952926
  },
  {
    "epoch": 13,
    "loss": 1.1080402249097825
  },
  {
    "epoch": 14,
    "loss": 1.0697507327795028
  },
  {
    "epoch": 15,
    "loss": 1.074429883956909
  },
  {
    "epoch": 16,
    "loss": 1.0612711226940155
  },
  {
    "epoch": 17,
    "loss": 1.0796763521432877
  },
  {
    "epoch": 18,
    "loss": 1.0506022769212722
  },
  {
    "epoch": 19,
    "loss": 1.0726463067531586
  },
  {
    "epoch": 20,
    "loss": 1.0581993746757508
  },
  {
    "epoch": 21,
    "loss": 1.025600375533104
  },
  {
    "epoch": 22,
    "loss": 1.0266253387928008
  },
  {
    "epoch": 23,
    "loss": 1.0322298526763916
  },
  {
    "epoch": 24,
    "loss": 1.0090094083547592
  },
  {
    "epoch": 25,
    "loss": 1.0131491386890412
  },
  {
    "epoch": 26,
    "loss": 1.0247562807798385
  },
  {
    "epoch": 27,
    "loss": 1.035086172223091
  },
  {
    "epoch": 28,
    "loss": 0.9974181026220321
  },
  {
    "epoch": 29,
    "loss": 1.0213759690523148
  },
  {
    "epoch": 30,
    "loss": 1.0516533696651458
  },
  {
    "epoch": 31,
    "loss": 1.0196929913759232
  },
  {
    "epoch": 32,
    "loss": 1.020316110253334
  },
  {
    "epoch": 33,
    "loss": 0.9947934073209762
  },
  {
    "epoch": 34,
    "loss": 0.9931758087873459
  },
  {
    "epoch": 35,
    "loss": 1.01300574362278
  },
  {
    "epoch": 36,
    "loss": 0.9861463248729706
  },
  {
    "epoch": 37,
    "loss": 1.0112288725376128
  },
  {
    "epoch": 38,
    "loss": 1.0021470028162003
  },
  {
    "epoch": 39,
    "loss": 1.0207917928695678
  },
  {
    "epoch": 40,
    "loss": 1.0162623864412308
  },
  {
    "epoch": 41,
    "loss": 1.0005694150924682
  },
  {
    "epoch": 42,
    "loss": 0.9783083081245423
  },
  {
    "epoch": 43,
    "loss": 0.9969039112329483
  },
  {
    "epoch": 44,
    "loss": 0.9808559650182724
  },
  {
    "epoch": 45,
    "loss": 0.994435116648674
  },
  {
    "epoch": 46,
    "loss": 0.9957420092821121
  },
  {
    "epoch": 47,
    "loss": 0.9672322469949722
  },
  {
    "epoch": 48,
    "loss": 1.000398384332657
  },
  {
    "epoch": 49,
    "loss": 0.9780198776721954
  },
  {
    "epoch": 50,
    "loss": 0.9914708334207535
  },
  {
    "epoch": 51,
    "loss": 0.9679004383087159
  },
  {
    "epoch": 52,
    "loss": 0.9778402692079544
  },
  {
    "epoch": 53,
    "loss": 0.9772179090976715
  },
  {
    "epoch": 54,
    "loss": 0.9653107154369355
  },
  {
    "epoch": 55,
    "loss": 0.9731667274236679
  },
  {
    "epoch": 56,
    "loss": 0.949379563331604
  },
  {
    "epoch": 57,
    "loss": 0.9749770748615265
  },
  {
    "epoch": 58,
    "loss": 0.9521992629766465
  },
  {
    "epoch": 59,
    "loss": 0.9667895889282226
  },
  {
    "epoch": 60,
    "loss": 0.986188018321991
  },
  {
    "epoch": 61,
    "loss": 0.9602873396873474
  },
  {
    "epoch": 62,
    "loss": 0.9559423685073852
  },
  {
    "epoch": 63,
    "loss": 0.9418599414825439
  },
  {
    "epoch": 64,
    "loss": 0.9401047778129578
  },
  {
    "epoch": 65,
    "loss": 0.9746890825033188
  },
  {
    "epoch": 66,
    "loss": 0.9660523933172226
  },
  {
    "epoch": 67,
    "loss": 0.9382032036781311
  },
  {
    "epoch": 68,
    "loss": 0.9610387712717057
  },
  {
    "epoch": 69,
    "loss": 0.9454307025671005
  },
  {
    "epoch": 70,
    "loss": 0.9601057988405227
  },
  {
    "epoch": 71,
    "loss": 0.9594235962629318
  },
  {
    "epoch": 72,
    "loss": 0.9345213520526886
  },
  {
    "epoch": 73,
    "loss": 0.945164367556572
  },
  {
    "epoch": 74,
    "loss": 0.9565669190883637
  },
  {
    "epoch": 75,
    "loss": 0.9565953028202057
  },
  {
    "epoch": 76,
    "loss": 0.9426741892099381
  },
  {
    "epoch": 77,
    "loss": 0.9372478771209717
  },
  {
    "epoch": 78,
    "loss": 0.9340982031822205
  },
  {
    "epoch": 79,
    "loss": 0.9240512543916702
  },
  {
    "epoch": 80,
    "loss": 0.9410276794433594
  },
  {
    "epoch": 81,
    "loss": 0.9323532199859619
  },
  {
    "epoch": 82,
    "loss": 0.930645210146904
  },
  {
    "epoch": 83,
    "loss": 0.9410226440429688
  },
  {
    "epoch": 84,
    "loss": 0.9428006434440612
  },
  {
    "epoch": 85,
    "loss": 0.9534425437450409
  },
  {
    "epoch": 86,
    "loss": 0.9226811712980271
  },
  {
    "epoch": 87,
    "loss": 0.9014470702409745
  },
  {
    "epoch": 88,
    "loss": 0.9303202491998672
  },
  {
    "epoch": 89,
    "loss": 0.9296999901533127
  },
  {
    "epoch": 90,
    "loss": 0.9522495597600937
  },
  {
    "epoch": 91,
    "loss": 0.8997685074806213
  },
  {
    "epoch": 92,
    "loss": 0.9220571583509445
  },
  {
    "epoch": 93,
    "loss": 0.9109075629711151
  },
  {
    "epoch": 94,
    "loss": 0.9205518251657486
  },
  {
    "epoch": 95,
    "loss": 0.9164002507925033
  },
  {
    "epoch": 96,
    "loss": 0.8859837663173675
  },
  {
    "epoch": 97,
    "loss": 0.9117435622215271
  },
  {
    "epoch": 98,
    "loss": 0.9142363345623017
  },
  {
    "epoch": 99,
    "loss": 0.9037272369861603
  },
  {
    "epoch": 100,
    "loss": 0.9121217769384384
  },
  {
    "epoch": 101,
    "loss": 0.902887235879898
  },
  {
    "epoch": 102,
    "loss": 0.9072003674507141
  },
  {
    "epoch": 103,
    "loss": 0.9157845836877823
  },
  {
    "epoch": 104,
    "loss": 0.9132463037967682
  },
  {
    "epoch": 105,
    "loss": 0.8823730093240738
  },
  {
    "epoch": 106,
    "loss": 0.8954607433080674
  },
  {
    "epoch": 107,
    "loss": 0.8859049713611603
  },
  {
    "epoch": 108,
    "loss": 0.9148761647939682
  },
  {
    "epoch": 109,
    "loss": 0.8931682181358337
  },
  {
    "epoch": 110,
    "loss": 0.8779062104225158
  },
  {
    "epoch": 111,
    "loss": 0.87486623108387
  },
  {
    "epoch": 112,
    "loss": 0.8908474898338318
  },
  {
    "epoch": 113,
    "loss": 0.8795519626140594
  },
  {
    "epoch": 114,
    "loss": 0.8647640204429626
  },
  {
    "epoch": 115,
    "loss": 0.8959596633911133
  },
  {
    "epoch": 116,
    "loss": 0.8682316273450852
  },
  {
    "epoch": 117,
    "loss": 0.8689764511585235
  },
  {
    "epoch": 118,
    "loss": 0.8857819300889969
  },
  {
    "epoch": 119,
    "loss": 0.8769959503412247
  },
  {
    "epoch": 120,
    "loss": 0.8587076985836029
  },
  {
    "epoch": 121,
    "loss": 0.8631371289491654
  },
  {
    "epoch": 122,
    "loss": 0.8645384049415589
  },
  {
    "epoch": 123,
    "loss": 0.8800580370426178
  },
  {
    "epoch": 124,
    "loss": 0.8894105613231659
  },
  {
    "epoch": 125,
    "loss": 0.8543491762876511
  },
  {
    "epoch": 126,
    "loss": 0.8586092221736908
  },
  {
    "epoch": 127,
    "loss": 0.8400196725130081
  },
  {
    "epoch": 128,
    "loss": 0.8679530775547027
  },
  {
    "epoch": 129,
    "loss": 0.8734125989675522
  },
  {
    "epoch": 130,
    "loss": 0.866539734005928
  },
  {
    "epoch": 131,
    "loss": 0.862424304485321
  },
  {
    "epoch": 132,
    "loss": 0.8372952967882157
  },
  {
    "epoch": 133,
    "loss": 0.853079189658165
  },
  {
    "epoch": 134,
    "loss": 0.8438391816616059
  },
  {
    "epoch": 135,
    "loss": 0.8404978972673416
  },
  {
    "epoch": 136,
    "loss": 0.851701652109623
  },
  {
    "epoch": 137,
    "loss": 0.8170718580484391
  },
  {
    "epoch": 138,
    "loss": 0.8485609143972397
  },
  {
    "epoch": 139,
    "loss": 0.8487307870388031
  },
  {
    "epoch": 140,
    "loss": 0.853476168513298
  },
  {
    "epoch": 141,
    "loss": 0.8418785065412522
  },
  {
    "epoch": 142,
    "loss": 0.8444200450181961
  },
  {
    "epoch": 143,
    "loss": 0.8233243536949157
  },
  {
    "epoch": 144,
    "loss": 0.8426504021883011
  },
  {
    "epoch": 145,
    "loss": 0.8480245929956436
  },
  {
    "epoch": 146,
    "loss": 0.831169776916504
  },
  {
    "epoch": 147,
    "loss": 0.796558667421341
  },
  {
    "epoch": 148,
    "loss": 0.8294175267219543
  },
  {
    "epoch": 149,
    "loss": 0.826152994632721
  },
  {
    "epoch": 150,
    "loss": 0.8263680869340897
  },
  {
    "epoch": 151,
    "loss": 0.8192164796590805
  },
  {
    "epoch": 152,
    "loss": 0.7941047576069832
  },
  {
    "epoch": 153,
    "loss": 0.807596253156662
  },
  {
    "epoch": 154,
    "loss": 0.8176493144035339
  },
  {
    "epoch": 155,
    "loss": 0.806556971669197
  },
  {
    "epoch": 156,
    "loss": 0.8047985357046127
  },
  {
    "epoch": 157,
    "loss": 0.815768306851387
  },
  {
    "epoch": 158,
    "loss": 0.828702278137207
  },
  {
    "epoch": 159,
    "loss": 0.8141563791036606
  },
  {
    "epoch": 160,
    "loss": 0.8062431651353836
  },
  {
    "epoch": 161,
    "loss": 0.792680345773697
  },
  {
    "epoch": 162,
    "loss": 0.8039673548936844
  },
  {
    "epoch": 163,
    "loss": 0.8048149740695953
  },
  {
    "epoch": 164,
    "loss": 0.7862325310707092
  },
  {
    "epoch": 165,
    "loss": 0.8032354572415352
  },
  {
    "epoch": 166,
    "loss": 0.7787924933433533
  },
  {
    "epoch": 167,
    "loss": 0.7974068933725357
  },
  {
    "epoch": 168,
    "loss": 0.8052453899383545
  },
  {
    "epoch": 169,
    "loss": 0.7838689550757408
  },
  {
    "epoch": 170,
    "loss": 0.7929699838161468
  },
  {
    "epoch": 171,
    "loss": 0.7812542980909347
  },
  {
    "epoch": 172,
    "loss": 0.7787845277786255
  },
  {
    "epoch": 173,
    "loss": 0.8096893659234047
  },
  {
    "epoch": 174,
    "loss": 0.7882980462908745
  },
  {
    "epoch": 175,
    "loss": 0.7901269626617432
  },
  {
    "epoch": 176,
    "loss": 0.7756644329428672
  },
  {
    "epoch": 177,
    "loss": 0.7665430524945259
  },
  {
    "epoch": 178,
    "loss": 0.7550007367134094
  },
  {
    "epoch": 179,
    "loss": 0.7783808171749115
  },
  {
    "epoch": 180,
    "loss": 0.7919395178556442
  },
  {
    "epoch": 181,
    "loss": 0.7706663140654564
  },
  {
    "epoch": 182,
    "loss": 0.7831152191758156
  },
  {
    "epoch": 183,
    "loss": 0.7615549933910369
  },
  {
    "epoch": 184,
    "loss": 0.7649196636676788
  },
  {
    "epoch": 185,
    "loss": 0.7729869255423546
  },
  {
    "epoch": 186,
    "loss": 0.7473048093914986
  },
  {
    "epoch": 187,
    "loss": 0.7648034733533859
  },
  {
    "epoch": 188,
    "loss": 0.7594041565060615
  },
  {
    "epoch": 189,
    "loss": 0.760200666487217
  },
  {
    "epoch": 190,
    "loss": 0.7553813496232032
  },
  {
    "epoch": 191,
    "loss": 0.7509760981798173
  },
  {
    "epoch": 192,
    "loss": 0.749590824842453
  },
  {
    "epoch": 193,
    "loss": 0.740036546587944
  },
  {
    "epoch": 194,
    "loss": 0.7626694276928901
  },
  {
    "epoch": 195,
    "loss": 0.740632854104042
  },
  {
    "epoch": 196,
    "loss": 0.7507246306538582
  },
  {
    "epoch": 197,
    "loss": 0.7603491672873497
  },
  {
    "epoch": 198,
    "loss": 0.7362695613503456
  },
  {
    "epoch": 199,
    "loss": 0.732815987765789
  },
  {
    "epoch": 200,
    "loss": 0.7406087690591812
  },
  {
    "epoch": 201,
    "loss": 0.7412673181295395
  },
  {
    "epoch": 202,
    "loss": 0.7346591794490814
  },
  {
    "epoch": 203,
    "loss": 0.7376218965649605
  },
  {
    "epoch": 204,
    "loss": 0.7349626722931862
  },
  {
    "epoch": 205,
    "loss": 0.7495841011404991
  },
  {
    "epoch": 206,
    "loss": 0.7363929617404937
  },
  {
    "epoch": 207,
    "loss": 0.719882672727108
  },
  {
    "epoch": 208,
    "loss": 0.735773554444313
  },
  {
    "epoch": 209,
    "loss": 0.7178955441713333
  },
  {
    "epoch": 210,
    "loss": 0.728873328268528
  },
  {
    "epoch": 211,
    "loss": 0.7439097005128861
  },
  {
    "epoch": 212,
    "loss": 0.7315603616833687
  },
  {
    "epoch": 213,
    "loss": 0.7267937704920768
  },
  {
    "epoch": 214,
    "loss": 0.7163544434309006
  },
  {
    "epoch": 215,
    "loss": 0.7294265675544739
  },
  {
    "epoch": 216,
    "loss": 0.705893630683422
  },
  {
    "epoch": 217,
    "loss": 0.72068726927042
  },
  {
    "epoch": 218,
    "loss": 0.7115208208560944
  },
  {
    "epoch": 219,
    "loss": 0.7330409169197083
  },
  {
    "epoch": 220,
    "loss": 0.7038681662082672
  },
  {
    "epoch": 221,
    "loss": 0.7068757614493371
  },
  {
    "epoch": 222,
    "loss": 0.7056248259544372
  },
  {
    "epoch": 223,
    "loss": 0.7114559531211853
  },
  {
    "epoch": 224,
    "loss": 0.6989794048666954
  },
  {
    "epoch": 225,
    "loss": 0.698523488342762
  },
  {
    "epoch": 226,
    "loss": 0.7085268199443817
  },
  {
    "epoch": 227,
    "loss": 0.6930415791273117
  },
  {
    "epoch": 228,
    "loss": 0.6973459121584892
  },
  {
    "epoch": 229,
    "loss": 0.6866368970274925
  },
  {
    "epoch": 230,
    "loss": 0.7071270582079887
  },
  {
    "epoch": 231,
    "loss": 0.696231025159359
  },
  {
    "epoch": 232,
    "loss": 0.684439762532711
  },
  {
    "epoch": 233,
    "loss": 0.6767631790041924
  },
  {
    "epoch": 234,
    "loss": 0.6875888106226921
  },
  {
    "epoch": 235,
    "loss": 0.6758681020140648
  },
  {
    "epoch": 236,
    "loss": 0.6934648367762566
  },
  {
    "epoch": 237,
    "loss": 0.6731130117177964
  },
  {
    "epoch": 238,
    "loss": 0.6740552744269371
  },
  {
    "epoch": 239,
    "loss": 0.6904425776004791
  },
  {
    "epoch": 240,
    "loss": 0.6710713675618172
  },
  {
    "epoch": 241,
    "loss": 0.677221935391426
  },
  {
    "epoch": 242,
    "loss": 0.6988113483786583
  },
  {
    "epoch": 243,
    "loss": 0.6925336784124374
  },
  {
    "epoch": 244,
    "loss": 0.6633853623270989
  },
  {
    "epoch": 245,
    "loss": 0.6769886264204978
  },
  {
    "epoch": 246,
    "loss": 0.6748611059784889
  },
  {
    "epoch": 247,
    "loss": 0.6454957833886147
  },
  {
    "epoch": 248,
    "loss": 0.6630498081445694
  },
  {
    "epoch": 249,
    "loss": 0.6620090585947037
  },
  {
    "epoch": 250,
    "loss": 0.6559764397144318
  },
  {
    "epoch": 251,
    "loss": 0.6663898310065269
  },
  {
    "epoch": 252,
    "loss": 0.66365737169981
  },
  {
    "epoch": 253,
    "loss": 0.6587192425131798
  },
  {
    "epoch": 254,
    "loss": 0.6497469913959503
  },
  {
    "epoch": 255,
    "loss": 0.6428797936439514
  },
  {
    "epoch": 256,
    "loss": 0.6637340900301933
  },
  {
    "epoch": 257,
    "loss": 0.6600138521194459
  },
  {
    "epoch": 258,
    "loss": 0.6610492160916328
  },
  {
    "epoch": 259,
    "loss": 0.6396523037552834
  },
  {
    "epoch": 260,
    "loss": 0.6427295449376106
  },
  {
    "epoch": 261,
    "loss": 0.648047367632389
  },
  {
    "epoch": 262,
    "loss": 0.6478111672401429
  },
  {
    "epoch": 263,
    "loss": 0.6624313196539879
  },
  {
    "epoch": 264,
    "loss": 0.6411045497655868
  },
  {
    "epoch": 265,
    "loss": 0.6284850159287453
  },
  {
    "epoch": 266,
    "loss": 0.6560987603664398
  },
  {
    "epoch": 267,
    "loss": 0.6465891253948212
  },
  {
    "epoch": 268,
    "loss": 0.6461025530099869
  },
  {
    "epoch": 269,
    "loss": 0.6464940014481545
  },
  {
    "epoch": 270,
    "loss": 0.6216531762480736
  },
  {
    "epoch": 271,
    "loss": 0.6247803983092308
  },
  {
    "epoch": 272,
    "loss": 0.6178421172499656
  },
  {
    "epoch": 273,
    "loss": 0.6179057365655899
  },
  {
    "epoch": 274,
    "loss": 0.6246624055504799
  },
  {
    "epoch": 275,
    "loss": 0.629111952483654
  },
  {
    "epoch": 276,
    "loss": 0.6276813942193985
  },
  {
    "epoch": 277,
    "loss": 0.6278947645425796
  },
  {
    "epoch": 278,
    "loss": 0.6237619292736053
  },
  {
    "epoch": 279,
    "loss": 0.6212051030993462
  },
  {
    "epoch": 280,
    "loss": 0.6218487596511841
  },
  {
    "epoch": 281,
    "loss": 0.6052431985735893
  },
  {
    "epoch": 282,
    "loss": 0.6199375459551811
  },
  {
    "epoch": 283,
    "loss": 0.6204138451814651
  },
  {
    "epoch": 284,
    "loss": 0.6127083775401115
  },
  {
    "epoch": 285,
    "loss": 0.6243612030148507
  },
  {
    "epoch": 286,
    "loss": 0.615263179242611
  },
  {
    "epoch": 287,
    "loss": 0.6093505424261093
  },
  {
    "epoch": 288,
    "loss": 0.6066505539417267
  },
  {
    "epoch": 289,
    "loss": 0.6178740760684014
  },
  {
    "epoch": 290,
    "loss": 0.5916182664036751
  },
  {
    "epoch": 291,
    "loss": 0.6032417973876
  },
  {
    "epoch": 292,
    "loss": 0.6032448735833168
  },
  {
    "epoch": 293,
    "loss": 0.6133613952994347
  },
  {
    "epoch": 294,
    "loss": 0.5977518090605736
  },
  {
    "epoch": 295,
    "loss": 0.6070182383060455
  },
  {
    "epoch": 296,
    "loss": 0.5861067906022072
  },
  {
    "epoch": 297,
    "loss": 0.5914870753884316
  },
  {
    "epoch": 298,
    "loss": 0.595711542069912
  },
  {
    "epoch": 299,
    "loss": 0.5936640295386314
  },
  {
    "epoch": 300,
    "loss": 0.5850889387726784
  },
  {
    "epoch": 301,
    "loss": 0.5972000378370285
  },
  {
    "epoch": 302,
    "loss": 0.5856311920285225
  },
  {
    "epoch": 303,
    "loss": 0.5916095405817032
  },
  {
    "epoch": 304,
    "loss": 0.5777111282944679
  },
  {
    "epoch": 305,
    "loss": 0.5834727513790131
  },
  {
    "epoch": 306,
    "loss": 0.5790520361065865
  },
  {
    "epoch": 307,
    "loss": 0.5776039692759514
  },
  {
    "epoch": 308,
    "loss": 0.5890500834584236
  },
  {
    "epoch": 309,
    "loss": 0.5685762494802475
  },
  {
    "epoch": 310,
    "loss": 0.5965642109513283
  },
  {
    "epoch": 311,
    "loss": 0.5861548396945
  },
  {
    "epoch": 312,
    "loss": 0.567006709575653
  },
  {
    "epoch": 313,
    "loss": 0.5675065016746521
  },
  {
    "epoch": 314,
    "loss": 0.5657541573047637
  },
  {
    "epoch": 315,
    "loss": 0.577660296857357
  },
  {
    "epoch": 316,
    "loss": 0.5822013720870018
  },
  {
    "epoch": 317,
    "loss": 0.5738366204500198
  },
  {
    "epoch": 318,
    "loss": 0.5524020072817802
  },
  {
    "epoch": 319,
    "loss": 0.5625245222449302
  },
  {
    "epoch": 320,
    "loss": 0.5722755694389343
  },
  {
    "epoch": 321,
    "loss": 0.5683342769742012
  },
  {
    "epoch": 322,
    "loss": 0.5600378894805909
  },
  {
    "epoch": 323,
    "loss": 0.5565021395683288
  },
  {
    "epoch": 324,
    "loss": 0.5706335058808327
  },
  {
    "epoch": 325,
    "loss": 0.561107357442379
  },
  {
    "epoch": 326,
    "loss": 0.5456930088996887
  },
  {
    "epoch": 327,
    "loss": 0.5675382417440414
  },
  {
    "epoch": 328,
    "loss": 0.5511184358596801
  },
  {
    "epoch": 329,
    "loss": 0.5459895649552345
  },
  {
    "epoch": 330,
    "loss": 0.5630571505427361
  },
  {
    "epoch": 331,
    "loss": 0.5379340940713883
  },
  {
    "epoch": 332,
    "loss": 0.533399170935154
  },
  {
    "epoch": 333,
    "loss": 0.5576387682557106
  },
  {
    "epoch": 334,
    "loss": 0.5389749711751938
  },
  {
    "epoch": 335,
    "loss": 0.5494487309455871
  },
  {
    "epoch": 336,
    "loss": 0.5363995510339737
  },
  {
    "epoch": 337,
    "loss": 0.5483122321963311
  },
  {
    "epoch": 338,
    "loss": 0.5322793516516685
  },
  {
    "epoch": 339,
    "loss": 0.5419164544343948
  },
  {
    "epoch": 340,
    "loss": 0.5372654610872268
  },
  {
    "epoch": 341,
    "loss": 0.5275012066960335
  },
  {
    "epoch": 342,
    "loss": 0.5356129282712936
  },
  {
    "epoch": 343,
    "loss": 0.525919860303402
  },
  {
    "epoch": 344,
    "loss": 0.520433312356472
  },
  {
    "epoch": 345,
    "loss": 0.5247808691859245
  },
  {
    "epoch": 346,
    "loss": 0.5327742904424667
  },
  {
    "epoch": 347,
    "loss": 0.5213787865638733
  },
  {
    "epoch": 348,
    "loss": 0.5138014775514602
  },
  {
    "epoch": 349,
    "loss": 0.5237879112362862
  },
  {
    "epoch": 350,
    "loss": 0.5221388107538223
  },
  {
    "epoch": 351,
    "loss": 0.5322681024670601
  },
  {
    "epoch": 352,
    "loss": 0.5070269346237183
  },
  {
    "epoch": 353,
    "loss": 0.5291050168871879
  },
  {
    "epoch": 354,
    "loss": 0.5085702174901963
  },
  {
    "epoch": 355,
    "loss": 0.5155247363448143
  },
  {
    "epoch": 356,
    "loss": 0.5121519902348518
  },
  {
    "epoch": 357,
    "loss": 0.5038801044225693
  },
  {
    "epoch": 358,
    "loss": 0.5174064114689827
  },
  {
    "epoch": 359,
    "loss": 0.5064453941583633
  },
  {
    "epoch": 360,
    "loss": 0.518844490647316
  },
  {
    "epoch": 361,
    "loss": 0.5087366017699242
  },
  {
    "epoch": 362,
    "loss": 0.5078220757842064
  },
  {
    "epoch": 363,
    "loss": 0.5048605206608773
  },
  {
    "epoch": 364,
    "loss": 0.5095590779185295
  },
  {
    "epoch": 365,
    "loss": 0.4924793893098831
  },
  {
    "epoch": 366,
    "loss": 0.502017180621624
  },
  {
    "epoch": 367,
    "loss": 0.4840079367160797
  },
  {
    "epoch": 368,
    "loss": 0.5118831780552864
  },
  {
    "epoch": 369,
    "loss": 0.4963246187567711
  },
  {
    "epoch": 370,
    "loss": 0.49430050104856493
  },
  {
    "epoch": 371,
    "loss": 0.4941349440813065
  },
  {
    "epoch": 372,
    "loss": 0.5025924521684647
  },
  {
    "epoch": 373,
    "loss": 0.4917555856704712
  },
  {
    "epoch": 374,
    "loss": 0.4845643410086632
  },
  {
    "epoch": 375,
    "loss": 0.5046194723248482
  },
  {
    "epoch": 376,
    "loss": 0.4943043312430382
  },
  {
    "epoch": 377,
    "loss": 0.4849116416275501
  }
]