[
  {
    "epoch": 1,
    "loss": 7.035823299884796
  },
  {
    "epoch": 2,
    "loss": 2.36098904132843
  },
  {
    "epoch": 3,
    "loss": 0.9359982919692993
  },
  {
    "epoch": 4,
    "loss": 0.8253210371732712
  },
  {
    "epoch": 5,
    "loss": 0.7371800634264946
  },
  {
    "epoch": 6,
    "loss": 0.7389922004938125
  },
  {
    "epoch": 7,
    "loss": 0.7035595020651817
  },
  {
    "epoch": 8,
    "loss": 0.6828187671303749
  },
  {
    "epoch": 9,
    "loss": 0.6782717090845108
  },
  {
    "epoch": 10,
    "loss": 0.6556469470262527
  },
  {
    "epoch": 11,
    "loss": 0.6340278297662735
  },
  {
    "epoch": 12,
    "loss": 0.6543465265631676
  },
  {
    "epoch": 13,
    "loss": 0.6198789712786674
  },
  {
    "epoch": 14,
    "loss": 0.6064843854308128
  },
  {
    "epoch": 15,
    "loss": 0.6440286481380463
  },
  {
    "epoch": 16,
    "loss": 0.6189338049292564
  },
  {
    "epoch": 17,
    "loss": 0.626834799349308
  },
  {
    "epoch": 18,
    "loss": 0.6069271621108056
  },
  {
    "epoch": 19,
    "loss": 0.5852763605117798
  },
  {
    "epoch": 20,
    "loss": 0.5992600518465042
  },
  {
    "epoch": 21,
    "loss": 0.5812478494644165
  },
  {
    "epoch": 22,
    "loss": 0.584566380083561
  },
  {
    "epoch": 23,
    "loss": 0.5879305323958397
  },
  {
    "epoch": 24,
    "loss": 0.5807975959777832
  },
  {
    "epoch": 25,
    "loss": 0.5743286424875259
  },
  {
    "epoch": 26,
    "loss": 0.5773261213302612
  },
  {
    "epoch": 27,
    "loss": 0.5795248192548752
  },
  {
    "epoch": 28,
    "loss": 0.5746957796812058
  },
  {
    "epoch": 29,
    "loss": 0.5591861090064049
  },
  {
    "epoch": 30,
    "loss": 0.5721118581295014
  },
  {
    "epoch": 31,
    "loss": 0.562965792119503
  },
  {
    "epoch": 32,
    "loss": 0.5798365712165833
  },
  {
    "epoch": 33,
    "loss": 0.5654914081096649
  },
  {
    "epoch": 34,
    "loss": 0.5582384407520294
  },
  {
    "epoch": 35,
    "loss": 0.5591014060378074
  },
  {
    "epoch": 36,
    "loss": 0.5661207410693169
  },
  {
    "epoch": 37,
    "loss": 0.5486020717024803
  },
  {
    "epoch": 38,
    "loss": 0.5611800479888917
  },
  {
    "epoch": 39,
    "loss": 0.5452636033296585
  },
  {
    "epoch": 40,
    "loss": 0.5626335570216179
  },
  {
    "epoch": 41,
    "loss": 0.5662726151943207
  },
  {
    "epoch": 42,
    "loss": 0.5484169089794159
  },
  {
    "epoch": 43,
    "loss": 0.5416828770935536
  },
  {
    "epoch": 44,
    "loss": 0.5442449393868446
  },
  {
    "epoch": 45,
    "loss": 0.5453401184082032
  },
  {
    "epoch": 46,
    "loss": 0.548057750761509
  },
  {
    "epoch": 47,
    "loss": 0.5358054494857788
  },
  {
    "epoch": 48,
    "loss": 0.5492565581202506
  },
  {
    "epoch": 49,
    "loss": 0.5283958873152733
  },
  {
    "epoch": 50,
    "loss": 0.5353553894162179
  },
  {
    "epoch": 51,
    "loss": 0.5435074955224991
  },
  {
    "epoch": 52,
    "loss": 0.5368859082460403
  },
  {
    "epoch": 53,
    "loss": 0.5347472697496414
  },
  {
    "epoch": 54,
    "loss": 0.5275206312537193
  },
  {
    "epoch": 55,
    "loss": 0.5359556287527084
  },
  {
    "epoch": 56,
    "loss": 0.5291175484657288
  },
  {
    "epoch": 57,
    "loss": 0.5224951297044754
  },
  {
    "epoch": 58,
    "loss": 0.5284532096982002
  },
  {
    "epoch": 59,
    "loss": 0.5232452261447906
  },
  {
    "epoch": 60,
    "loss": 0.5315001475811004
  },
  {
    "epoch": 61,
    "loss": 0.5294959783554077
  },
  {
    "epoch": 62,
    "loss": 0.5187164449691772
  },
  {
    "epoch": 63,
    "loss": 0.5342084082961083
  },
  {
    "epoch": 64,
    "loss": 0.5148328155279159
  },
  {
    "epoch": 65,
    "loss": 0.5160748744010926
  },
  {
    "epoch": 66,
    "loss": 0.5177104046940804
  },
  {
    "epoch": 67,
    "loss": 0.5209353238344192
  },
  {
    "epoch": 68,
    "loss": 0.5120264968276024
  },
  {
    "epoch": 69,
    "loss": 0.5184119254350662
  },
  {
    "epoch": 70,
    "loss": 0.5173817130923272
  },
  {
    "epoch": 71,
    "loss": 0.5031598943471909
  },
  {
    "epoch": 72,
    "loss": 0.50629997164011
  },
  {
    "epoch": 73,
    "loss": 0.5132357975840569
  },
  {
    "epoch": 74,
    "loss": 0.4950733962655067
  },
  {
    "epoch": 75,
    "loss": 0.5190125924348831
  },
  {
    "epoch": 76,
    "loss": 0.5052072864770889
  },
  {
    "epoch": 77,
    "loss": 0.493859176337719
  },
  {
    "epoch": 78,
    "loss": 0.5012612000107766
  },
  {
    "epoch": 79,
    "loss": 0.4952495828270912
  },
  {
    "epoch": 80,
    "loss": 0.4892702484130859
  },
  {
    "epoch": 81,
    "loss": 0.5085641774535179
  },
  {
    "epoch": 82,
    "loss": 0.5013296020030975
  },
  {
    "epoch": 83,
    "loss": 0.5025990936160087
  },
  {
    "epoch": 84,
    "loss": 0.49843709617853166
  },
  {
    "epoch": 85,
    "loss": 0.4929551169276237
  },
  {
    "epoch": 86,
    "loss": 0.5070273363590241
  },
  {
    "epoch": 87,
    "loss": 0.5007558327913284
  },
  {
    "epoch": 88,
    "loss": 0.4859841433167458
  },
  {
    "epoch": 89,
    "loss": 0.4955692878365517
  },
  {
    "epoch": 90,
    "loss": 0.49501717418432234
  },
  {
    "epoch": 91,
    "loss": 0.4870548376441002
  },
  {
    "epoch": 92,
    "loss": 0.4887705984711647
  },
  {
    "epoch": 93,
    "loss": 0.4857367631793022
  },
  {
    "epoch": 94,
    "loss": 0.4962084555625916
  },
  {
    "epoch": 95,
    "loss": 0.47986715257167817
  },
  {
    "epoch": 96,
    "loss": 0.49724395483732226
  },
  {
    "epoch": 97,
    "loss": 0.4872019010782242
  },
  {
    "epoch": 98,
    "loss": 0.4890115839242935
  },
  {
    "epoch": 99,
    "loss": 0.4838652122020721
  },
  {
    "epoch": 100,
    "loss": 0.4780375790596008
  },
  {
    "epoch": 101,
    "loss": 0.47666860193014143
  },
  {
    "epoch": 102,
    "loss": 0.4853967797756195
  },
  {
    "epoch": 103,
    "loss": 0.4885078126192093
  },
  {
    "epoch": 104,
    "loss": 0.49261284589767457
  },
  {
    "epoch": 105,
    "loss": 0.47894735455513
  },
  {
    "epoch": 106,
    "loss": 0.47772341400384905
  },
  {
    "epoch": 107,
    "loss": 0.4743883627653122
  },
  {
    "epoch": 108,
    "loss": 0.4793459638953209
  },
  {
    "epoch": 109,
    "loss": 0.47487290263175963
  },
  {
    "epoch": 110,
    "loss": 0.4915409106016159
  },
  {
    "epoch": 111,
    "loss": 0.4702883240580559
  },
  {
    "epoch": 112,
    "loss": 0.46663899093866346
  },
  {
    "epoch": 113,
    "loss": 0.4667417967319489
  },
  {
    "epoch": 114,
    "loss": 0.46979107677936555
  },
  {
    "epoch": 115,
    "loss": 0.4645382735133171
  },
  {
    "epoch": 116,
    "loss": 0.4624193868041038
  },
  {
    "epoch": 117,
    "loss": 0.4765535345673561
  },
  {
    "epoch": 118,
    "loss": 0.4747071897983551
  },
  {
    "epoch": 119,
    "loss": 0.47631042122840883
  },
  {
    "epoch": 120,
    "loss": 0.46668256193399427
  },
  {
    "epoch": 121,
    "loss": 0.4638673162460327
  },
  {
    "epoch": 122,
    "loss": 0.4753481811285019
  },
  {
    "epoch": 123,
    "loss": 0.47450086534023284
  },
  {
    "epoch": 124,
    "loss": 0.4625494986772537
  },
  {
    "epoch": 125,
    "loss": 0.4643222439289093
  },
  {
    "epoch": 126,
    "loss": 0.4726350498199463
  }
]