[
  {
    "epoch": 1,
    "loss": 7.874175637960434
  },
  {
    "epoch": 2,
    "loss": 1.3157332976162435
  },
  {
    "epoch": 3,
    "loss": 0.21974227219820022
  },
  {
    "epoch": 4,
    "loss": 0.18231383919715882
  },
  {
    "epoch": 5,
    "loss": 0.16737909324467182
  },
  {
    "epoch": 6,
    "loss": 0.15560918785631656
  },
  {
    "epoch": 7,
    "loss": 0.14444392129778863
  },
  {
    "epoch": 8,
    "loss": 0.14646242681890725
  },
  {
    "epoch": 9,
    "loss": 0.12678061805665494
  },
  {
    "epoch": 10,
    "loss": 0.11739326823502778
  },
  {
    "epoch": 11,
    "loss": 0.11231814544647932
  },
  {
    "epoch": 12,
    "loss": 0.11306423123925924
  },
  {
    "epoch": 13,
    "loss": 0.10748158857226371
  },
  {
    "epoch": 14,
    "loss": 0.1042794406041503
  },
  {
    "epoch": 15,
    "loss": 0.10671353414654731
  },
  {
    "epoch": 16,
    "loss": 0.0991119909286499
  },
  {
    "epoch": 17,
    "loss": 0.10039731193333865
  },
  {
    "epoch": 18,
    "loss": 0.0989947260543704
  },
  {
    "epoch": 19,
    "loss": 0.09148675475269556
  },
  {
    "epoch": 20,
    "loss": 0.09449572097510099
  },
  {
    "epoch": 21,
    "loss": 0.09476201221346855
  },
  {
    "epoch": 22,
    "loss": 0.09025843244045972
  },
  {
    "epoch": 23,
    "loss": 0.08736545868217944
  },
  {
    "epoch": 24,
    "loss": 0.08651691865175963
  },
  {
    "epoch": 25,
    "loss": 0.08963199779391288
  },
  {
    "epoch": 26,
    "loss": 0.08723397552967072
  },
  {
    "epoch": 27,
    "loss": 0.08748987771570682
  },
  {
    "epoch": 28,
    "loss": 0.0846956879273057
  },
  {
    "epoch": 29,
    "loss": 0.08360702633857726
  },
  {
    "epoch": 30,
    "loss": 0.08100088991224766
  },
  {
    "epoch": 31,
    "loss": 0.08049729198217392
  },
  {
    "epoch": 32,
    "loss": 0.07728783655911683
  },
  {
    "epoch": 33,
    "loss": 0.08166992340236902
  },
  {
    "epoch": 34,
    "loss": 0.07908191833645105
  },
  {
    "epoch": 35,
    "loss": 0.07739025048911571
  },
  {
    "epoch": 36,
    "loss": 0.07944852720946073
  },
  {
    "epoch": 37,
    "loss": 0.0765772707387805
  },
  {
    "epoch": 38,
    "loss": 0.07553770307451486
  },
  {
    "epoch": 39,
    "loss": 0.07580913797020912
  },
  {
    "epoch": 40,
    "loss": 0.07704787366092206
  },
  {
    "epoch": 41,
    "loss": 0.07422811545431614
  },
  {
    "epoch": 42,
    "loss": 0.073299669791013
  },
  {
    "epoch": 43,
    "loss": 0.07512248437851668
  },
  {
    "epoch": 44,
    "loss": 0.07378717929124833
  },
  {
    "epoch": 45,
    "loss": 0.07818420199677348
  },
  {
    "epoch": 46,
    "loss": 0.0717657227627933
  },
  {
    "epoch": 47,
    "loss": 0.07089561570435762
  },
  {
    "epoch": 48,
    "loss": 0.07115857228636742
  },
  {
    "epoch": 49,
    "loss": 0.07032001629471779
  },
  {
    "epoch": 50,
    "loss": 0.06808834329247475
  },
  {
    "epoch": 51,
    "loss": 0.07229942066594958
  },
  {
    "epoch": 52,
    "loss": 0.06793365642428398
  },
  {
    "epoch": 53,
    "loss": 0.06820394147187471
  },
  {
    "epoch": 54,
    "loss": 0.07558708097785712
  },
  {
    "epoch": 55,
    "loss": 0.0662066520191729
  },
  {
    "epoch": 56,
    "loss": 0.07131898485124111
  },
  {
    "epoch": 57,
    "loss": 0.06841511590406299
  },
  {
    "epoch": 58,
    "loss": 0.0650921636633575
  },
  {
    "epoch": 59,
    "loss": 0.0657114983536303
  },
  {
    "epoch": 60,
    "loss": 0.06643947914242744
  },
  {
    "epoch": 61,
    "loss": 0.06258137553930282
  },
  {
    "epoch": 62,
    "loss": 0.06484532874077559
  },
  {
    "epoch": 63,
    "loss": 0.06422732016071678
  },
  {
    "epoch": 64,
    "loss": 0.064778419341892
  },
  {
    "epoch": 65,
    "loss": 0.06582851922139525
  },
  {
    "epoch": 66,
    "loss": 0.061776306852698325
  },
  {
    "epoch": 67,
    "loss": 0.06488070629537106
  },
  {
    "epoch": 68,
    "loss": 0.06300799045711755
  },
  {
    "epoch": 69,
    "loss": 0.06480739334598183
  },
  {
    "epoch": 70,
    "loss": 0.0622759472951293
  },
  {
    "epoch": 71,
    "loss": 0.06311820903792978
  },
  {
    "epoch": 72,
    "loss": 0.05927725965157151
  },
  {
    "epoch": 73,
    "loss": 0.06180162677541375
  },
  {
    "epoch": 74,
    "loss": 0.06238865949213505
  },
  {
    "epoch": 75,
    "loss": 0.05918022479861975
  },
  {
    "epoch": 76,
    "loss": 0.06072179296985269
  },
  {
    "epoch": 77,
    "loss": 0.05819567834958434
  },
  {
    "epoch": 78,
    "loss": 0.05879150522872806
  },
  {
    "epoch": 79,
    "loss": 0.05999136954545975
  },
  {
    "epoch": 80,
    "loss": 0.057697614282369615
  },
  {
    "epoch": 81,
    "loss": 0.057000024095177654
  },
  {
    "epoch": 82,
    "loss": 0.05817635226994753
  },
  {
    "epoch": 83,
    "loss": 0.05848037354648113
  },
  {
    "epoch": 84,
    "loss": 0.0565989650413394
  },
  {
    "epoch": 85,
    "loss": 0.05883232947438955
  },
  {
    "epoch": 86,
    "loss": 0.05840697204694152
  },
  {
    "epoch": 87,
    "loss": 0.055631261207163336
  },
  {
    "epoch": 88,
    "loss": 0.057581006996333596
  },
  {
    "epoch": 89,
    "loss": 0.059674159232527016
  },
  {
    "epoch": 90,
    "loss": 0.05306955290958285
  },
  {
    "epoch": 91,
    "loss": 0.05785038644447923
  },
  {
    "epoch": 92,
    "loss": 0.05814911922439933
  },
  {
    "epoch": 93,
    "loss": 0.05222005415707827
  },
  {
    "epoch": 94,
    "loss": 0.05366473058238626
  },
  {
    "epoch": 95,
    "loss": 0.053301265314221385
  },
  {
    "epoch": 96,
    "loss": 0.053777297269552944
  },
  {
    "epoch": 97,
    "loss": 0.054717241786420345
  },
  {
    "epoch": 98,
    "loss": 0.05412762243300676
  },
  {
    "epoch": 99,
    "loss": 0.058448394257575274
  },
  {
    "epoch": 100,
    "loss": 0.053446927219629285
  },
  {
    "epoch": 101,
    "loss": 0.0520398037135601
  },
  {
    "epoch": 102,
    "loss": 0.05277162734419107
  },
  {
    "epoch": 103,
    "loss": 0.053602666109800336
  },
  {
    "epoch": 104,
    "loss": 0.053765243794769046
  },
  {
    "epoch": 105,
    "loss": 0.05117274412885308
  },
  {
    "epoch": 106,
    "loss": 0.051404649559408426
  },
  {
    "epoch": 107,
    "loss": 0.05282742135226726
  },
  {
    "epoch": 108,
    "loss": 0.05224037393927574
  },
  {
    "epoch": 109,
    "loss": 0.05208611644804478
  },
  {
    "epoch": 110,
    "loss": 0.051046841517090796
  },
  {
    "epoch": 111,
    "loss": 0.049281596578657626
  },
  {
    "epoch": 112,
    "loss": 0.04897085687145591
  },
  {
    "epoch": 113,
    "loss": 0.05108083663508296
  },
  {
    "epoch": 114,
    "loss": 0.047860800996422766
  },
  {
    "epoch": 115,
    "loss": 0.04897857928648591
  },
  {
    "epoch": 116,
    "loss": 0.04893698589876294
  },
  {
    "epoch": 117,
    "loss": 0.05038551267236471
  },
  {
    "epoch": 118,
    "loss": 0.04749095745384693
  },
  {
    "epoch": 119,
    "loss": 0.04926170002669096
  },
  {
    "epoch": 120,
    "loss": 0.04787316946312785
  },
  {
    "epoch": 121,
    "loss": 0.052409210074692965
  },
  {
    "epoch": 122,
    "loss": 0.05312100378796458
  },
  {
    "epoch": 123,
    "loss": 0.04844828894361854
  },
  {
    "epoch": 124,
    "loss": 0.04833602271974087
  },
  {
    "epoch": 125,
    "loss": 0.04897471057251096
  },
  {
    "epoch": 126,
    "loss": 0.045374742895364764
  },
  {
    "epoch": 127,
    "loss": 0.047397440392524005
  },
  {
    "epoch": 128,
    "loss": 0.05027362886816263
  },
  {
    "epoch": 129,
    "loss": 0.04474118120968342
  },
  {
    "epoch": 130,
    "loss": 0.04637507235631347
  },
  {
    "epoch": 131,
    "loss": 0.046810931768268345
  },
  {
    "epoch": 132,
    "loss": 0.04669136402197182
  },
  {
    "epoch": 133,
    "loss": 0.04592522220686078
  },
  {
    "epoch": 134,
    "loss": 0.04488501369953155
  },
  {
    "epoch": 135,
    "loss": 0.04548051001504064
  },
  {
    "epoch": 136,
    "loss": 0.04524720611050725
  },
  {
    "epoch": 137,
    "loss": 0.04557410903275013
  },
  {
    "epoch": 138,
    "loss": 0.04710961213335395
  },
  {
    "epoch": 139,
    "loss": 0.04943296435289085
  }
]